{
  "action": "arith-div",
  "resourceKind": "adversarial",
  "filter": {
    "kind": "KIND_CONDITIONAL",
    "condition": {
      "expression": {
        "operator": "eq",
        "operands": [
          {
            "expression": {
              "operator": "div",
              "operands": [
                {
                  "variable": "request.resource.attr.aNumber"
                },
                {
                  "value": 2
                }
              ]
            }
          },
          {
            "value": 1
          }
        ]
      }
    }
  }
}
